azure/mgmt/astro/__init__.py
azure/mgmt/astro/_astro_mgmt_client.py
azure/mgmt/astro/_configuration.py
azure/mgmt/astro/_patch.py
azure/mgmt/astro/_serialization.py
azure/mgmt/astro/_vendor.py
azure/mgmt/astro/_version.py
azure/mgmt/astro/py.typed
azure/mgmt/astro/aio/__init__.py
azure/mgmt/astro/aio/_astro_mgmt_client.py
azure/mgmt/astro/aio/_configuration.py
azure/mgmt/astro/aio/_patch.py
azure/mgmt/astro/aio/operations/__init__.py
azure/mgmt/astro/aio/operations/_operations.py
azure/mgmt/astro/aio/operations/_organizations_operations.py
azure/mgmt/astro/aio/operations/_patch.py
azure/mgmt/astro/models/__init__.py
azure/mgmt/astro/models/_astro_mgmt_client_enums.py
azure/mgmt/astro/models/_models_py3.py
azure/mgmt/astro/models/_patch.py
azure/mgmt/astro/operations/__init__.py
azure/mgmt/astro/operations/_operations.py
azure/mgmt/astro/operations/_organizations_operations.py
azure/mgmt/astro/operations/_patch.py
azure_mgmt_astro-1.0.0b1.dist-info/LICENSE
azure_mgmt_astro-1.0.0b1.dist-info/METADATA
azure_mgmt_astro-1.0.0b1.dist-info/WHEEL
azure_mgmt_astro-1.0.0b1.dist-info/top_level.txt
azure_mgmt_astro-1.0.0b1.dist-info/RECORD
